pydict2latex/__init__.py
pydict2latex/py2tex.py
pydict2latex/variables2dict.py
pydict2latex-0.0.2.dist-info/LICENSE
pydict2latex-0.0.2.dist-info/METADATA
pydict2latex-0.0.2.dist-info/WHEEL
pydict2latex-0.0.2.dist-info/top_level.txt
pydict2latex-0.0.2.dist-info/RECORD
