Metadata-Version: 2.1
Name: pydict2latex
Version: 0.0.2
Summary: Acces python dictionaries from latex
Home-page: https://github.com/m-damien/PyDictToLatex
Author: Damien Masson
License: BSD 2-clause
Classifier: Intended Audience :: Science/Research
Classifier: License :: OSI Approved :: BSD License
Classifier: Operating System :: OS Independent
Classifier: Topic :: Text Processing :: Markup :: LaTeX
License-File: LICENSE
Requires-Dist: numpy
